muscle_bids/__init__.py
muscle_bids/dcm2mbids.py
muscle_bids/config/__init__.py
muscle_bids/config/tag_definitions.py
muscle_bids/converters/__init__.py
muscle_bids/converters/abstract_converter.py
muscle_bids/converters/megre_ge.py
muscle_bids/converters/mese_philips.py
muscle_bids/converters/mese_siemens.py
muscle_bids/converters/quantitative_maps.py
muscle_bids/dosma_io/__init__.py
muscle_bids/dosma_io/device.py
muscle_bids/dosma_io/dosma_defaults.py
muscle_bids/dosma_io/dosma_io_utils.py
muscle_bids/dosma_io/env.py
muscle_bids/dosma_io/med_volume.py
muscle_bids/dosma_io/numpy_routines.py
muscle_bids/dosma_io/orientation.py
muscle_bids/dosma_io/io/__init__.py
muscle_bids/dosma_io/io/dicom_io.py
muscle_bids/dosma_io/io/format_io.py
muscle_bids/dosma_io/io/format_io_utils.py
muscle_bids/dosma_io/io/nifti_io.py
muscle_bids/utils/__init__.py
muscle_bids/utils/headers.py
muscle_bids/utils/image.py
muscle_bids/utils/io.py
muscle_bids-0.0.2.dist-info/LICENSE
muscle_bids-0.0.2.dist-info/METADATA
muscle_bids-0.0.2.dist-info/WHEEL
muscle_bids-0.0.2.dist-info/entry_points.txt
muscle_bids-0.0.2.dist-info/top_level.txt
muscle_bids-0.0.2.dist-info/RECORD
