Metadata-Version: 2.1
Name: muscle-bids
Version: 0.0.2
Summary: Library for standardized data input/output for muscle MR imaging, based on BIDS
Home-page: https://github.com/muscle-bids/muscle-bids
Author: Francesco Santini
Author-email: francesco.santini@unibas.ch
Project-URL: Bug Tracker, https://github.com/muscle-bids/muscle-bids/issuesleproject/issues
Classifier: Programming Language :: Python :: 3
Classifier: License :: OSI Approved :: GNU General Public License v3 or later (GPLv3+)
Classifier: Operating System :: OS Independent
Requires-Python: >=3.6
License-File: LICENSE
Requires-Dist: bidict
Requires-Dist: natsort
Requires-Dist: nibabel
Requires-Dist: numpy
Requires-Dist: scipy
Requires-Dist: packaging
Requires-Dist: pydicom
Requires-Dist: tqdm
